django_graphene_crud_generator/AbstractCrudGraphQLGenerator.py
django_graphene_crud_generator/CrudBuildPhaseEnum.py
django_graphene_crud_generator/IGraphQLEndpointComponent.py
django_graphene_crud_generator/__init__.py
django_graphene_crud_generator/types.py
django_graphene_crud_generator/version.py
django_graphene_crud_generator/crud_generator/AbstractGraphQLCrudComponent.py
django_graphene_crud_generator/crud_generator/ReadStandardMixIn.py
django_graphene_crud_generator/crud_generator/__init__.py
django_graphene_crud_generator/crud_generator/contexts.py
django_graphene_crud_generator/crud_generator/create_components.py
django_graphene_crud_generator/crud_generator/crud_generators.py
django_graphene_crud_generator/crud_generator/delete_components.py
django_graphene_crud_generator/crud_generator/mixins.py
django_graphene_crud_generator/crud_generator/read_components.py
django_graphene_crud_generator/crud_generator/shared_components.py
django_graphene_crud_generator/crud_generator/update_components.py
django_graphene_crud_generator/generator/AbstractCreateGraphQLMutationGenerator.py
django_graphene_crud_generator/generator/AbstractDeleteGraphQLMutationGenerator.py
django_graphene_crud_generator/generator/AbstractGraphQLEndpointGenerator.py
django_graphene_crud_generator/generator/AbstractGraphQLMutationGenerator.py
django_graphene_crud_generator/generator/AbstractGraphQLQueryGenerator.py
django_graphene_crud_generator/generator/AbstractReadGraphQLQueryGenerator.py
django_graphene_crud_generator/generator/AbstractUpdateGraphQLMutationGenerator.py
django_graphene_crud_generator/generator/IGraphQLEndpointGenerator.py
django_graphene_crud_generator/generator/LambdaGraphQLMutationGenerator.py
django_graphene_crud_generator/generator/LambdaGraphQLQueryGenerator.py
django_graphene_crud_generator/generator/PermissionsComponent.py
django_graphene_crud_generator/generator/TokenBasedAuthenticationComponent.py
django_graphene_crud_generator/generator/__init__.py
django_graphene_crud_generator-1.7.10.dist-info/LICENSE.md
django_graphene_crud_generator-1.7.10.dist-info/METADATA
django_graphene_crud_generator-1.7.10.dist-info/WHEEL
django_graphene_crud_generator-1.7.10.dist-info/top_level.txt
django_graphene_crud_generator-1.7.10.dist-info/RECORD
